{
  "url": "https://www.salesforce.com/blog/announcing-marketing-champions/?bc=DB",
  "slug": "announcing-marketing-champions",
  "title": "Let’s Celebrate the 2025 Marketing Champions",
  "author": "Guilda Hilaire",
  "published_date": "2025-11-03T15:58:12+00:00",
  "section_analyses": [
    {
      "section_index": 0,
      "section_heading": "Introduction",
      "classification": {
        "reader_intent": "learning",
        "primary_persona": "business_leader",
        "secondary_persona": null,
        "funnel_stage": "awareness",
        "product_alignment": [
          "sales_cloud"
        ],
        "topic_tags": [
          "trailhead"
        ],
        "confidence": 0.75,
        "rationale": "Rule-based: learning intent detected in 'Introduction'. Products: sales_cloud. Funnel: awareness."
      },
      "existing_cta": null,
      "existing_cta_score": null,
      "recommendations": [],
      "recommend_no_cta": true,
      "no_cta_reason": "Introduction — let the reader engage with the content before presenting a CTA."
    },
    {
      "section_index": 1,
      "section_heading": "What makes a Marketing Champion?",
      "classification": {
        "reader_intent": "problem_solving",
        "primary_persona": "marketing_leader",
        "secondary_persona": "business_leader",
        "funnel_stage": "consideration",
        "product_alignment": [
          "sales_cloud",
          "marketing_cloud"
        ],
        "topic_tags": [
          "trailhead"
        ],
        "confidence": 0.75,
        "rationale": "Rule-based: problem_solving intent detected in 'What makes a Marketing Champion?'. Products: sales_cloud, marketing_cloud. Funnel: consideration."
      },
      "existing_cta": {
        "heading": "Want to become a Marketing Champion?",
        "body": "Calling all #MomentMarketers, social savants, and campaign captains — take your career to the next level by applying for Salesforce’s Marketing Champions program.",
        "button_text": "Apply today",
        "button_url": "https://www.salesforce.com/campaign/champions/marketing/?sfdc-redirect=410",
        "position_after_section": 1
      },
      "existing_cta_score": {
        "relevance_score": 1.0,
        "funnel_alignment": "match",
        "persona_match": "match",
        "product_alignment": "match",
        "issues": [],
        "rationale": "CTA targets consideration-stage readers; section is consideration-stage. Product alignment: match."
      },
      "recommendations": [],
      "recommend_no_cta": true,
      "no_cta_reason": "Narrative section — CTA not needed here. Effective CTAs are placed after value delivery, not during."
    },
    {
      "section_index": 2,
      "section_heading": "How can I connect with the Marketing Champions?",
      "classification": {
        "reader_intent": "learning",
        "primary_persona": "marketing_leader",
        "secondary_persona": "business_leader",
        "funnel_stage": "awareness",
        "product_alignment": [
          "sales_cloud",
          "marketing_cloud"
        ],
        "topic_tags": [
          "collaboration"
        ],
        "confidence": 0.75,
        "rationale": "Rule-based: learning intent detected in 'How can I connect with the Marketing Champions?'. Products: sales_cloud, marketing_cloud. Funnel: awareness."
      },
      "existing_cta": {
        "heading": "Ready to take the next step?",
        "body": "Join our Marketing Cloud Trailblazer Community today, and you can connect with fellow marketing professionals, share your thoughts, and grow your career.",
        "button_text": "Here's your invite",
        "button_url": "https://trailhead.salesforce.com/trailblazer-community/groups/0F9300000001pQ5CAI?tab=discussion&sort=LAST_MODIFIED_DATE_DESC",
        "position_after_section": 2
      },
      "existing_cta_score": {
        "relevance_score": 1.0,
        "funnel_alignment": "match",
        "persona_match": "match",
        "product_alignment": "match",
        "issues": [],
        "rationale": "CTA targets awareness-stage readers; section is awareness-stage. Product alignment: match."
      },
      "recommendations": [],
      "recommend_no_cta": true,
      "no_cta_reason": "Short narrative section — CTA would interrupt the reading flow."
    }
  ],
  "overall_health_score": 0.9,
  "cta_health_score": 90,
  "cta_health_grade": "excellent",
  "cta_health_breakdown": {
    "quantity": 25,
    "placement": 30,
    "intent_match": 30,
    "ux": 10,
    "penalties": -5
  },
  "cta_health_issues": [
    "CTAs in 67% of sections. Consider reducing to 1 per 3-4 sections."
  ],
  "misaligned_count": 1
}