{
  "url": "https://blog.hubspot.com/marketing/ai-workflow-automation-tools",
  "slug": "ai-workflow-automation-tools",
  "title": "Best AI workflow automation tools for growing businesses",
  "author": "Jennifer Clark",
  "published_date": "2026-02-18",
  "section_analyses": [
    {
      "section_index": 0,
      "section_heading": "Introduction",
      "classification": {
        "reader_intent": "problem_solving",
        "primary_persona": "business_leader",
        "secondary_persona": "marketing_leader",
        "funnel_stage": "decision",
        "product_alignment": [
          "sales_cloud",
          "marketing_cloud"
        ],
        "topic_tags": [
          "crm",
          "ai_tools",
          "data_analytics",
          "productivity"
        ],
        "confidence": 0.75,
        "rationale": "Rule-based: problem_solving intent detected in 'Introduction'. Products: sales_cloud, marketing_cloud. Funnel: decision."
      },
      "existing_cta": null,
      "existing_cta_score": null,
      "recommendations": [],
      "recommend_no_cta": true,
      "no_cta_reason": "Introduction — let the reader engage with the content before presenting a CTA."
    },
    {
      "section_index": 1,
      "section_heading": "What are AI workflow automation tools, and how do they work?",
      "classification": {
        "reader_intent": "learning",
        "primary_persona": "marketing_leader",
        "secondary_persona": "small_business_owner",
        "funnel_stage": "awareness",
        "product_alignment": [
          "agentforce",
          "sales_cloud",
          "marketing_cloud",
          "slack"
        ],
        "topic_tags": [
          "ai_agents",
          "ai_tools",
          "data_analytics",
          "productivity"
        ],
        "confidence": 0.75,
        "rationale": "Rule-based: learning intent detected in 'What are AI workflow automation tools, and how do they work?'. Products: agentforce, sales_cloud, marketing_cloud, slack. Funnel: awareness."
      },
      "existing_cta": null,
      "existing_cta_score": null,
      "recommendations": [],
      "recommend_no_cta": true,
      "no_cta_reason": "Short narrative section — CTA would interrupt the reading flow."
    },
    {
      "section_index": 2,
      "section_heading": "Free Marketing Software",
      "classification": {
        "reader_intent": "learning",
        "primary_persona": "marketing_leader",
        "secondary_persona": "small_business_owner",
        "funnel_stage": "awareness",
        "product_alignment": [
          "marketing_cloud"
        ],
        "topic_tags": [
          "ai_tools",
          "marketing_automation"
        ],
        "confidence": 0.75,
        "rationale": "Rule-based: learning intent detected in 'Free Marketing Software'. Products: marketing_cloud. Funnel: awareness."
      },
      "existing_cta": null,
      "existing_cta_score": null,
      "recommendations": [],
      "recommend_no_cta": true,
      "no_cta_reason": "Section too short for a CTA."
    },
    {
      "section_index": 3,
      "section_heading": "Agents vs. Automated AI workflows: What’s the difference?",
      "classification": {
        "reader_intent": "problem_solving",
        "primary_persona": "business_leader",
        "secondary_persona": "small_business_owner",
        "funnel_stage": "consideration",
        "product_alignment": [
          "agentforce",
          "sales_cloud"
        ],
        "topic_tags": [
          "ai_agents",
          "crm",
          "data_analytics",
          "productivity",
          "thought_leadership"
        ],
        "confidence": 0.75,
        "rationale": "Rule-based: problem_solving intent detected in 'Agents vs. Automated AI workflows: What’s the difference?'. Products: agentforce, sales_cloud. Funnel: consideration."
      },
      "existing_cta": null,
      "existing_cta_score": null,
      "recommendations": [],
      "recommend_no_cta": true,
      "no_cta_reason": "Narrative section — CTA not needed here. Effective CTAs are placed after value delivery, not during."
    },
    {
      "section_index": 4,
      "section_heading": "How to Choose an AI Workflow Automation Tool",
      "classification": {
        "reader_intent": "problem_solving",
        "primary_persona": "business_leader",
        "secondary_persona": "developer",
        "funnel_stage": "consideration",
        "product_alignment": [
          "sales_cloud",
          "platform"
        ],
        "topic_tags": [
          "crm",
          "customer_service",
          "data_analytics",
          "platform"
        ],
        "confidence": 0.75,
        "rationale": "Rule-based: problem_solving intent detected in 'How to Choose an AI Workflow Automation Tool'. Products: sales_cloud, platform. Funnel: consideration."
      },
      "existing_cta": null,
      "existing_cta_score": null,
      "recommendations": [],
      "recommend_no_cta": true,
      "no_cta_reason": "Narrative section — CTA not needed here. Effective CTAs are placed after value delivery, not during."
    },
    {
      "section_index": 5,
      "section_heading": "Evaluation Criteria by Growth Stage",
      "classification": {
        "reader_intent": "implementing",
        "primary_persona": "developer",
        "secondary_persona": "business_leader",
        "funnel_stage": "consideration",
        "product_alignment": [
          "sales_cloud",
          "platform"
        ],
        "topic_tags": [
          "small_business",
          "crm",
          "data_analytics",
          "productivity",
          "security",
          "collaboration"
        ],
        "confidence": 0.75,
        "rationale": "Rule-based: implementing intent detected in 'Evaluation Criteria by Growth Stage'. Products: sales_cloud, platform. Funnel: consideration."
      },
      "existing_cta": null,
      "existing_cta_score": null,
      "recommendations": [
        {
          "type": "cta",
          "cta_id": "wtl",
          "score": 0.85,
          "match_rationale": "CTA targets sales_cloud at consideration stage for consideration-stage developer reader."
        },
        {
          "type": "trail",
          "trail_id": "trail-get-started-with-omnistudio-on-the-salesforce-platform",
          "name": "Get Started with Omnistudio on the Salesforce Platform",
          "url": "https://trailhead.salesforce.com/content/learn/trails/get-started-with-omnistudio-on-the-salesforce-platform",
          "duration_minutes": 190,
          "score": 0.65,
          "match_rationale": "Trail targets platform at decision stage for consideration-stage developer reader."
        },
        {
          "type": "trail",
          "trail_id": "trail-boost-sales-efficiency-with-revenue-cloud",
          "name": "Boost Sales Efficiency with Agentforce Revenue Management",
          "url": "https://trailhead.salesforce.com/content/learn/trails/boost-sales-efficiency-with-revenue-cloud",
          "duration_minutes": 285,
          "score": 0.55,
          "match_rationale": "Trail targets agentforce at consideration stage for consideration-stage developer reader."
        }
      ],
      "recommend_no_cta": false,
      "no_cta_reason": ""
    },
    {
      "section_index": 6,
      "section_heading": "Common Implementation Pitfalls",
      "classification": {
        "reader_intent": "problem_solving",
        "primary_persona": "business_leader",
        "secondary_persona": "small_business_owner",
        "funnel_stage": "consideration",
        "product_alignment": [
          "agentforce"
        ],
        "topic_tags": [
          "data_analytics"
        ],
        "confidence": 0.75,
        "rationale": "Rule-based: problem_solving intent detected in 'Common Implementation Pitfalls'. Products: agentforce. Funnel: consideration."
      },
      "existing_cta": null,
      "existing_cta_score": null,
      "recommendations": [],
      "recommend_no_cta": true,
      "no_cta_reason": "Narrative section — CTA not needed here. Effective CTAs are placed after value delivery, not during."
    },
    {
      "section_index": 7,
      "section_heading": "Best AI Workflow Automation Tools by Department",
      "classification": {
        "reader_intent": "learning",
        "primary_persona": "marketing_leader",
        "secondary_persona": "business_leader",
        "funnel_stage": "awareness",
        "product_alignment": [
          "sales_cloud",
          "marketing_cloud"
        ],
        "topic_tags": [
          "data_analytics",
          "productivity"
        ],
        "confidence": 0.75,
        "rationale": "Rule-based: learning intent detected in 'Best AI Workflow Automation Tools by Department'. Products: sales_cloud, marketing_cloud. Funnel: awareness."
      },
      "existing_cta": null,
      "existing_cta_score": null,
      "recommendations": [],
      "recommend_no_cta": true,
      "no_cta_reason": "Short narrative section — CTA would interrupt the reading flow."
    },
    {
      "section_index": 8,
      "section_heading": "Marketing",
      "classification": {
        "reader_intent": "problem_solving",
        "primary_persona": "marketing_leader",
        "secondary_persona": "developer",
        "funnel_stage": "awareness",
        "product_alignment": [
          "einstein_ai",
          "sales_cloud",
          "marketing_cloud",
          "slack"
        ],
        "topic_tags": [
          "small_business",
          "ai_tools",
          "data_analytics",
          "productivity",
          "collaboration",
          "platform"
        ],
        "confidence": 0.75,
        "rationale": "Rule-based: problem_solving intent detected in 'Marketing'. Products: einstein_ai, sales_cloud, marketing_cloud, slack. Funnel: awareness."
      },
      "existing_cta": null,
      "existing_cta_score": null,
      "recommendations": [],
      "recommend_no_cta": true,
      "no_cta_reason": "Narrative section — CTA not needed here. Effective CTAs are placed after value delivery, not during."
    },
    {
      "section_index": 9,
      "section_heading": "Free Marketing Software",
      "classification": {
        "reader_intent": "learning",
        "primary_persona": "marketing_leader",
        "secondary_persona": "small_business_owner",
        "funnel_stage": "awareness",
        "product_alignment": [
          "marketing_cloud"
        ],
        "topic_tags": [
          "ai_tools",
          "marketing_automation"
        ],
        "confidence": 0.75,
        "rationale": "Rule-based: learning intent detected in 'Free Marketing Software'. Products: marketing_cloud. Funnel: awareness."
      },
      "existing_cta": null,
      "existing_cta_score": null,
      "recommendations": [],
      "recommend_no_cta": true,
      "no_cta_reason": "Section too short for a CTA."
    },
    {
      "section_index": 10,
      "section_heading": "Sales",
      "classification": {
        "reader_intent": "problem_solving",
        "primary_persona": "sales_leader",
        "secondary_persona": "small_business_owner",
        "funnel_stage": "consideration",
        "product_alignment": [
          "sales_cloud",
          "service_cloud",
          "marketing_cloud"
        ],
        "topic_tags": [
          "small_business",
          "crm",
          "ai_tools",
          "sales_automation",
          "data_analytics",
          "productivity"
        ],
        "confidence": 0.75,
        "rationale": "Rule-based: problem_solving intent detected in 'Sales'. Products: sales_cloud, service_cloud, marketing_cloud. Funnel: consideration."
      },
      "existing_cta": null,
      "existing_cta_score": null,
      "recommendations": [
        {
          "type": "cta",
          "cta_id": "wtl",
          "score": 0.85,
          "match_rationale": "CTA targets sales_cloud at consideration stage for consideration-stage sales_leader reader."
        },
        {
          "type": "cta",
          "cta_id": "http:--join.serviceblazer.com",
          "score": 0.85,
          "match_rationale": "CTA targets service_cloud at consideration stage for consideration-stage sales_leader reader."
        },
        {
          "type": "trail",
          "trail_id": "trail-optimize-and-grow-your-use-of-marketing-cloud-engagement",
          "name": "Optimize and Grow Your Use of Marketing Cloud Engagement",
          "url": "https://trailhead.salesforce.com/content/learn/trails/optimize-and-grow-your-use-of-marketing-cloud-engagement",
          "duration_minutes": 741,
          "score": 0.85,
          "match_rationale": "Trail targets marketing_cloud at consideration stage for consideration-stage sales_leader reader."
        }
      ],
      "recommend_no_cta": false,
      "no_cta_reason": ""
    },
    {
      "section_index": 11,
      "section_heading": "Service",
      "classification": {
        "reader_intent": "problem_solving",
        "primary_persona": "service_leader",
        "secondary_persona": "business_leader",
        "funnel_stage": "consideration",
        "product_alignment": [
          "agentforce",
          "einstein_ai",
          "sales_cloud",
          "service_cloud"
        ],
        "topic_tags": [
          "small_business",
          "crm",
          "ai_tools",
          "customer_service",
          "data_analytics",
          "productivity"
        ],
        "confidence": 0.75,
        "rationale": "Rule-based: problem_solving intent detected in 'Service'. Products: agentforce, einstein_ai, sales_cloud, service_cloud. Funnel: consideration."
      },
      "existing_cta": null,
      "existing_cta_score": null,
      "recommendations": [
        {
          "type": "trail",
          "trail_id": "trail-boost-sales-efficiency-with-revenue-cloud",
          "name": "Boost Sales Efficiency with Agentforce Revenue Management",
          "url": "https://trailhead.salesforce.com/content/learn/trails/boost-sales-efficiency-with-revenue-cloud",
          "duration_minutes": 285,
          "score": 0.95,
          "match_rationale": "Trail targets agentforce at consideration stage for consideration-stage service_leader reader."
        },
        {
          "type": "cta",
          "cta_id": "wtl",
          "score": 0.85,
          "match_rationale": "CTA targets sales_cloud at consideration stage for consideration-stage service_leader reader."
        },
        {
          "type": "cta",
          "cta_id": "http:--join.serviceblazer.com",
          "score": 0.85,
          "match_rationale": "CTA targets service_cloud at consideration stage for consideration-stage service_leader reader."
        }
      ],
      "recommend_no_cta": false,
      "no_cta_reason": ""
    },
    {
      "section_index": 12,
      "section_heading": "Operations",
      "classification": {
        "reader_intent": "problem_solving",
        "primary_persona": "small_business_owner",
        "secondary_persona": "business_leader",
        "funnel_stage": "consideration",
        "product_alignment": [
          "einstein_ai",
          "sales_cloud",
          "slack",
          "platform"
        ],
        "topic_tags": [
          "small_business",
          "customer_service",
          "data_analytics",
          "productivity",
          "collaboration",
          "platform"
        ],
        "confidence": 0.75,
        "rationale": "Rule-based: problem_solving intent detected in 'Operations'. Products: einstein_ai, sales_cloud, slack, platform. Funnel: consideration."
      },
      "existing_cta": null,
      "existing_cta_score": null,
      "recommendations": [
        {
          "type": "cta",
          "cta_id": "wtl",
          "score": 0.85,
          "match_rationale": "CTA targets sales_cloud at consideration stage for consideration-stage small_business_owner reader."
        },
        {
          "type": "cta",
          "cta_id": "https:--join.slack.com-t-agentblazercommunity-shar",
          "score": 0.85,
          "match_rationale": "CTA targets slack at consideration stage for consideration-stage small_business_owner reader."
        },
        {
          "type": "trail",
          "trail_id": "trail-set-up-merchandising-for-your-storefront",
          "name": "Set Up Merchandising for Your Storefront",
          "url": "https://trailhead.salesforce.com/content/learn/trails/set-up-merchandising-for-your-storefront",
          "duration_minutes": 1010,
          "score": 0.85,
          "match_rationale": "Trail targets einstein_ai at consideration stage for consideration-stage small_business_owner reader."
        }
      ],
      "recommend_no_cta": false,
      "no_cta_reason": ""
    },
    {
      "section_index": 13,
      "section_heading": "Best AI Workflow Automation Tools by Growth Stage",
      "classification": {
        "reader_intent": "evaluating",
        "primary_persona": "developer",
        "secondary_persona": "business_leader",
        "funnel_stage": "consideration",
        "product_alignment": [
          "agentforce",
          "service_cloud",
          "slack",
          "platform"
        ],
        "topic_tags": [
          "ai_agents",
          "small_business",
          "customer_service",
          "data_analytics",
          "security",
          "collaboration"
        ],
        "confidence": 0.75,
        "rationale": "Rule-based: evaluating intent detected in 'Best AI Workflow Automation Tools by Growth Stage'. Products: agentforce, service_cloud, slack, platform. Funnel: consideration."
      },
      "existing_cta": null,
      "existing_cta_score": null,
      "recommendations": [
        {
          "type": "trail",
          "trail_id": "trail-agentforce-commerce-sell-everywhere-anytime",
          "name": "Agentforce Commerce: Sell Everywhere, Anytime",
          "url": "https://trailhead.salesforce.com/content/learn/trails/agentforce-commerce-sell-everywhere-anytime",
          "duration_minutes": 695,
          "score": 0.95,
          "match_rationale": "Trail targets agentforce at consideration stage for consideration-stage developer reader."
        },
        {
          "type": "cta",
          "cta_id": "http:--join.serviceblazer.com",
          "score": 0.85,
          "match_rationale": "CTA targets service_cloud at consideration stage for consideration-stage developer reader."
        },
        {
          "type": "cta",
          "cta_id": "https:--join.slack.com-t-agentblazercommunity-shar",
          "score": 0.85,
          "match_rationale": "CTA targets slack at consideration stage for consideration-stage developer reader."
        }
      ],
      "recommend_no_cta": false,
      "no_cta_reason": ""
    },
    {
      "section_index": 14,
      "section_heading": "How do I get started and scale AI workflow automation in my organization?",
      "classification": {
        "reader_intent": "implementing",
        "primary_persona": "marketing_leader",
        "secondary_persona": "business_leader",
        "funnel_stage": "decision",
        "product_alignment": [
          "sales_cloud",
          "marketing_cloud"
        ],
        "topic_tags": [
          "crm",
          "data_analytics"
        ],
        "confidence": 0.75,
        "rationale": "Rule-based: implementing intent detected in 'How do I get started and scale AI workflow automation in my organization?'. Products: sales_cloud, marketing_cloud. Funnel: decision."
      },
      "existing_cta": null,
      "existing_cta_score": null,
      "recommendations": [
        {
          "type": "cta",
          "cta_id": "form-signup-freetrial-salesforce-starter",
          "score": 0.85,
          "match_rationale": "CTA targets sales_cloud at decision stage for decision-stage marketing_leader reader."
        },
        {
          "type": "trail",
          "trail_id": "trail-configure-revenue-cloud",
          "name": "Configure Agentforce Revenue Management",
          "url": "https://trailhead.salesforce.com/content/learn/trails/configure-revenue-cloud",
          "duration_minutes": 1005,
          "score": 0.55,
          "match_rationale": "Trail targets agentforce at decision stage for decision-stage marketing_leader reader."
        },
        {
          "type": "trail",
          "trail_id": "trail-get-started-with-incident-response",
          "name": "Get Started with Incident Response",
          "url": "https://trailhead.salesforce.com/content/learn/trails/get-started-with-incident-response",
          "duration_minutes": 55,
          "score": 0.5,
          "match_rationale": "Trail targets general at decision stage for decision-stage marketing_leader reader."
        }
      ],
      "recommend_no_cta": false,
      "no_cta_reason": ""
    },
    {
      "section_index": 15,
      "section_heading": "Which tool is best for small teams with no developer resources?",
      "classification": {
        "reader_intent": "learning",
        "primary_persona": "developer",
        "secondary_persona": "small_business_owner",
        "funnel_stage": "awareness",
        "product_alignment": [
          "sales_cloud",
          "platform"
        ],
        "topic_tags": [
          "small_business",
          "productivity",
          "collaboration",
          "platform"
        ],
        "confidence": 0.75,
        "rationale": "Rule-based: learning intent detected in 'Which tool is best for small teams with no developer resources?'. Products: sales_cloud, platform. Funnel: awareness."
      },
      "existing_cta": null,
      "existing_cta_score": null,
      "recommendations": [],
      "recommend_no_cta": true,
      "no_cta_reason": "Short narrative section — CTA would interrupt the reading flow."
    },
    {
      "section_index": 16,
      "section_heading": "What is an AI workflow builder, and how is it different from an agent?",
      "classification": {
        "reader_intent": "learning",
        "primary_persona": "small_business_owner",
        "secondary_persona": "developer",
        "funnel_stage": "awareness",
        "product_alignment": [
          "agentforce",
          "sales_cloud",
          "slack"
        ],
        "topic_tags": [
          "ai_agents",
          "data_analytics",
          "productivity"
        ],
        "confidence": 0.75,
        "rationale": "Rule-based: learning intent detected in 'What is an AI workflow builder, and how is it different from an agent?'. Products: agentforce, sales_cloud, slack. Funnel: awareness."
      },
      "existing_cta": null,
      "existing_cta_score": null,
      "recommendations": [],
      "recommend_no_cta": true,
      "no_cta_reason": "Short narrative section — CTA would interrupt the reading flow."
    },
    {
      "section_index": 17,
      "section_heading": "Can AI automate end-to-end processes across multiple hubs?",
      "classification": {
        "reader_intent": "learning",
        "primary_persona": "small_business_owner",
        "secondary_persona": "business_leader",
        "funnel_stage": "awareness",
        "product_alignment": [
          "slack"
        ],
        "topic_tags": [
          "data_analytics",
          "productivity",
          "collaboration"
        ],
        "confidence": 0.75,
        "rationale": "Rule-based: learning intent detected in 'Can AI automate end-to-end processes across multiple hubs?'. Products: slack. Funnel: awareness."
      },
      "existing_cta": null,
      "existing_cta_score": null,
      "recommendations": [],
      "recommend_no_cta": true,
      "no_cta_reason": "Short narrative section — CTA would interrupt the reading flow."
    },
    {
      "section_index": 18,
      "section_heading": "How do I evaluate data privacy and security when using AI?",
      "classification": {
        "reader_intent": "learning",
        "primary_persona": "developer",
        "secondary_persona": "it_leader",
        "funnel_stage": "awareness",
        "product_alignment": [
          "platform"
        ],
        "topic_tags": [
          "data_analytics",
          "security",
          "platform",
          "trailhead"
        ],
        "confidence": 0.75,
        "rationale": "Rule-based: learning intent detected in 'How do I evaluate data privacy and security when using AI?'. Products: platform. Funnel: awareness."
      },
      "existing_cta": null,
      "existing_cta_score": null,
      "recommendations": [],
      "recommend_no_cta": true,
      "no_cta_reason": "Short narrative section — CTA would interrupt the reading flow."
    },
    {
      "section_index": 19,
      "section_heading": "When should I choose iPaaS or self-hosting over a low-code tool?",
      "classification": {
        "reader_intent": "evaluating",
        "primary_persona": "developer",
        "secondary_persona": "business_leader",
        "funnel_stage": "consideration",
        "product_alignment": [
          "platform",
          "mulesoft"
        ],
        "topic_tags": [
          "data_analytics",
          "collaboration",
          "platform"
        ],
        "confidence": 0.75,
        "rationale": "Rule-based: evaluating intent detected in 'When should I choose iPaaS or self-hosting over a low-code tool?'. Products: platform, mulesoft. Funnel: consideration."
      },
      "existing_cta": null,
      "existing_cta_score": null,
      "recommendations": [
        {
          "type": "trail",
          "trail_id": "trail-get-started-with-omnistudio-on-the-salesforce-platform",
          "name": "Get Started with Omnistudio on the Salesforce Platform",
          "url": "https://trailhead.salesforce.com/content/learn/trails/get-started-with-omnistudio-on-the-salesforce-platform",
          "duration_minutes": 190,
          "score": 0.65,
          "match_rationale": "Trail targets platform at decision stage for consideration-stage developer reader."
        },
        {
          "type": "trail",
          "trail_id": "trail-get-started-with-mulesoft-composer",
          "name": "Get Started with MuleSoft Composer",
          "url": "https://trailhead.salesforce.com/content/learn/trails/get-started-with-mulesoft-composer",
          "duration_minutes": 190,
          "score": 0.65,
          "match_rationale": "Trail targets mulesoft at decision stage for consideration-stage developer reader."
        },
        {
          "type": "trail",
          "trail_id": "trail-agentforce-commerce-sell-everywhere-anytime",
          "name": "Agentforce Commerce: Sell Everywhere, Anytime",
          "url": "https://trailhead.salesforce.com/content/learn/trails/agentforce-commerce-sell-everywhere-anytime",
          "duration_minutes": 695,
          "score": 0.55,
          "match_rationale": "Trail targets agentforce at consideration stage for consideration-stage developer reader."
        }
      ],
      "recommend_no_cta": false,
      "no_cta_reason": ""
    },
    {
      "section_index": 20,
      "section_heading": "Implementing AI Workflow Automation",
      "classification": {
        "reader_intent": "learning",
        "primary_persona": "business_leader",
        "secondary_persona": "developer",
        "funnel_stage": "awareness",
        "product_alignment": [
          "sales_cloud"
        ],
        "topic_tags": [
          "crm",
          "data_analytics",
          "thought_leadership",
          "platform"
        ],
        "confidence": 0.75,
        "rationale": "Rule-based: learning intent detected in 'Implementing AI Workflow Automation'. Products: sales_cloud. Funnel: awareness."
      },
      "existing_cta": null,
      "existing_cta_score": null,
      "recommendations": [],
      "recommend_no_cta": true,
      "no_cta_reason": "Narrative section — CTA not needed here. Effective CTAs are placed after value delivery, not during."
    },
    {
      "section_index": 21,
      "section_heading": "Free Marketing Software",
      "classification": {
        "reader_intent": "learning",
        "primary_persona": "marketing_leader",
        "secondary_persona": "small_business_owner",
        "funnel_stage": "awareness",
        "product_alignment": [
          "marketing_cloud"
        ],
        "topic_tags": [
          "ai_tools",
          "marketing_automation"
        ],
        "confidence": 0.75,
        "rationale": "Rule-based: learning intent detected in 'Free Marketing Software'. Products: marketing_cloud. Funnel: awareness."
      },
      "existing_cta": null,
      "existing_cta_score": null,
      "recommendations": [],
      "recommend_no_cta": true,
      "no_cta_reason": "Section too short for a CTA."
    },
    {
      "section_index": 22,
      "section_heading": "Don't forget to share this post!",
      "classification": {
        "reader_intent": "learning",
        "primary_persona": "marketing_leader",
        "secondary_persona": "business_leader",
        "funnel_stage": "awareness",
        "product_alignment": [
          "einstein_ai",
          "sales_cloud",
          "marketing_cloud"
        ],
        "topic_tags": [
          "ai_tools",
          "marketing_automation",
          "data_analytics",
          "collaboration",
          "trailhead"
        ],
        "confidence": 0.75,
        "rationale": "Rule-based: learning intent detected in 'Don't forget to share this post!'. Products: einstein_ai, sales_cloud, marketing_cloud. Funnel: awareness."
      },
      "existing_cta": {
        "heading": "",
        "body": "",
        "button_text": "Landing Page Creator",
        "button_url": "https://www.hubspot.com/free-business-tools/landing-page-gpt",
        "position_after_section": 22
      },
      "existing_cta_score": {
        "relevance_score": 0.65,
        "funnel_alignment": "adjacent",
        "persona_match": "match",
        "product_alignment": "partial",
        "issues": [
          "Product alignment is partial — a more targeted CTA may perform better"
        ],
        "rationale": "CTA targets consideration-stage readers; section is awareness-stage. Product alignment: partial."
      },
      "recommendations": [],
      "recommend_no_cta": true,
      "no_cta_reason": "Short narrative section — CTA would interrupt the reading flow."
    }
  ],
  "overall_health_score": 0.48,
  "cta_health_score": 48,
  "cta_health_grade": "poor",
  "cta_health_breakdown": {
    "quantity": 3,
    "placement": 10,
    "intent_match": 25,
    "ux": 10,
    "penalties": 0
  },
  "cta_health_issues": [
    "Too many CTAs (15). Research shows effectiveness drops after 3-4. Consider removing the weakest ones.",
    "CTA 'See pricing' targets decision readers but article is awareness-stage content."
  ],
  "misaligned_count": 2
}